README.md
setup.cfg
setup.py
UPnPy.egg-info/PKG-INFO
UPnPy.egg-info/SOURCES.txt
UPnPy.egg-info/dependency_links.txt
UPnPy.egg-info/top_level.txt
tests/__init__.py
tests/test_SSDPDevice.py
upnpy/__init__.py
upnpy/exceptions.py
upnpy/utils.py
upnpy/soap/SOAP.py
upnpy/soap/__init__.py
upnpy/ssdp/SSDPDevice.py
upnpy/ssdp/SSDPFilters.py
upnpy/ssdp/SSDPHeader.py
upnpy/ssdp/SSDPRequest.py
upnpy/ssdp/__init__.py
upnpy/upnp/UPnP.py
upnpy/upnp/__init__.py