Metadata-Version: 2.1
Name: UPnPy
Version: 1.1.0
Summary: Lightweight UPnP client library for Python.
Home-page: https://github.com/5kyc0d3r/upnpy
Author: 5kyc0d3r
Author-email: 5kyc0d3r@pm.me
License: MIT
Keywords: upnp,upnpy
Platform: UNKNOWN
Classifier: Development Status :: 5 - Production/Stable
Classifier: Intended Audience :: Developers
Classifier: License :: OSI Approved :: MIT License
Classifier: Programming Language :: Python :: 3.6
Classifier: Programming Language :: Python :: 3.7
